<?xml version="1.0" encoding="utf-8"?>
<LanguageData>
	<AnomaliesExpected.Speedometer.TurnPointer>Повернуть указатель на {0}</AnomaliesExpected.Speedometer.TurnPointer>
	<AnomaliesExpected.Speedometer.TurnPointerCurrent>Повернуть указатель на {0} [Текущий]</AnomaliesExpected.Speedometer.TurnPointerCurrent>
	<AnomaliesExpected.Speedometer.TurnPointerDisabled>Повернуть указатель на {0} [Недоступно]</AnomaliesExpected.Speedometer.TurnPointerDisabled>
	<AnomaliesExpected.Speedometer.TurnPointer.Label>Повернуть винт</AnomaliesExpected.Speedometer.TurnPointer.Label>
	<AnomaliesExpected.Speedometer.TurnPointer.Desc>Повернуть регулировочный винт чтобы переключить в другой режим</AnomaliesExpected.Speedometer.TurnPointer.Desc>
	
	<AnomaliesExpected.Speedometer.TakeOff>Снять {0}?</AnomaliesExpected.Speedometer.TakeOff>
	<AnomaliesExpected.Speedometer.TakeOff.Label>Снять</AnomaliesExpected.Speedometer.TakeOff.Label>
	<AnomaliesExpected.Speedometer.TakeOff.Desc>Снять {0} с себя</AnomaliesExpected.Speedometer.TakeOff.Desc>
</LanguageData>
